{
  "data": [
    {
      "country_id": 1,
      "country_code": "SY",
      "name": "Al-Hasakah",
      "code": "HA"
    },
    {
      "country_id": 1,
      "country_code": "SY",
      "name": "Al-Raqqah",
      "code": "RA"
    },
    {
      "country_id": 1,
      "country_code": "SY",
      "name": "Aleppo",
      "code": "HL"
    },
    {
      "country_id": 1,
      "country_code": "SY",
      "name": "As-Suwayda",
      "code": "SU"
    },
    {
      "country_id": 1,
      "country_code": "SY",
      "name": "Damascus",
      "code": "DI"
    },
    {
      "country_id": 1,
      "country_code": "SY",
      "name": "Daraa",
      "code": "DR"
    },
    {
      "country_id": 1,
      "country_code": "SY",
      "name": "Deir ez-Zor",
      "code": "DY"
    },
    {
      "country_id": 1,
      "country_code": "SY",
      "name": "Hama",
      "code": "HM"
    },
    {
      "country_id": 1,
      "country_code": "SY",
      "name": "Homs",
      "code": "HI"
    },
    {
      "country_id": 1,
      "country_code": "SY",
      "name": "Idlib",
      "code": "ID"
    },
    {
      "country_id": 1,
      "country_code": "SY",
      "name": "Latakia",
      "code": "LA"
    },
    {
      "country_id": 1,
      "country_code": "SY",
      "name": "Quneitra",
      "code": "QU"
    },
    {
      "country_id": 1,
      "country_code": "SY",
      "name": "Rif Dimashq",
      "code": "RD"
    },
    {
      "country_id": 1,
      "country_code": "SY",
      "name": "Tartus",
      "code": "TA"
    }
  ]
}